nebo_bot/__init__.py
nebo_bot/_hooks.py
nebo_bot/_links.py
nebo_bot/city.py
nebo_bot/core.py
nebo_bot/default_message_handler.py
nebo_bot/humans.py
nebo_bot/quest.py
nebo_bot/result_codes.py
nebo_bot/settings.py
nebo_bot/utils.py
nebo_bot/work.py
nebo_bot-0.0.8.3.1.dist-info/LICENSE
nebo_bot-0.0.8.3.1.dist-info/METADATA
nebo_bot-0.0.8.3.1.dist-info/WHEEL
nebo_bot-0.0.8.3.1.dist-info/top_level.txt
nebo_bot-0.0.8.3.1.dist-info/RECORD
