Metadata-Version: 2.1
Name: nebo-bot
Version: 0.0.8.3.1
Summary: This module makes to automatic game actions nebo.mobi
Home-page: https://gitlab.com/nmelis/nebo-bot
Author: NMelis
Author-email: nebo.game-bots@mail.space
License: UNKNOWN
Platform: UNKNOWN
Classifier: Programming Language :: Python :: 3
Classifier: License :: OSI Approved :: MIT License
Classifier: Operating System :: OS Independent
